setup.cfg
setup.py
torch_model_client/__init__.py
torch_model_client/client.py
torch_model_client/test_client.py
torch_model_client.egg-info/PKG-INFO
torch_model_client.egg-info/SOURCES.txt
torch_model_client.egg-info/dependency_links.txt
torch_model_client.egg-info/top_level.txt